MANIFEST.in
README.md
setup.py
examples/simple_scan.ipynb
guide_bot/__init__.py
guide_bot/_version.py
guide_bot.egg-info/PKG-INFO
guide_bot.egg-info/SOURCES.txt
guide_bot.egg-info/dependency_links.txt
guide_bot.egg-info/requires.txt
guide_bot.egg-info/top_level.txt
guide_bot/McStas_components/Conics_EH.comp
guide_bot/McStas_components/Conics_PH.comp
guide_bot/McStas_components/Conics_PP.comp
guide_bot/McStas_components/Guide_curved_gravity_safe.comp
guide_bot/McStas_components/conic.h
guide_bot/McStas_components/w1_conics.h
guide_bot/McStas_components/w1_general.h
guide_bot/base_elements/__init__.py
guide_bot/base_elements/base_element_geometry.py
guide_bot/base_elements/guide_elements.py
guide_bot/cluster/Base.py
guide_bot/cluster/SLURM.py
guide_bot/cluster/__init__.py
guide_bot/cluster_config/DMSC.yaml
guide_bot/elements/Element_curved.py
guide_bot/elements/Element_elliptic.py
guide_bot/elements/Element_gap.py
guide_bot/elements/Element_kink.py
guide_bot/elements/Element_slit.py
guide_bot/elements/Element_straight.py
guide_bot/elements/Element_wolter_EH.py
guide_bot/elements/Element_wolter_PH.py
guide_bot/elements/__init__.py
guide_bot/elements/geometry_register.py
guide_bot/logging/__init__.py
guide_bot/logging/guide_log.py
guide_bot/logging/log_plotter.py
guide_bot/logging/log_plotter_helpers.py
guide_bot/logging/overview.py
guide_bot/logic/DataCollector.py
guide_bot/logic/Guide.py
guide_bot/logic/Project.py
guide_bot/logic/__init__.py
guide_bot/logic/length_system.py
guide_bot/logic/line_of_sight.py
guide_bot/logic/runner.py
guide_bot/optimizer/__init__.py
guide_bot/optimizer/optimizer.py
guide_bot/parameters/__init__.py
guide_bot/parameters/constraints.py
guide_bot/parameters/instrument_parameter_container.py
guide_bot/parameters/instrument_parameters.py
guide_bot/requirements/__init__.py
guide_bot/requirements/input_configuration_iterator.py
guide_bot/requirements/requirement_parameters.py
guide_bot/scan_visualization/__init__.py
guide_bot/scan_visualization/base_jb_interface.py
guide_bot/scan_visualization/interface_any_monitor.py
guide_bot/scan_visualization/interface_compare_monitors.py
