Metadata-Version: 2.1
Name: guide-bot
Version: 0.0.33
Summary: Neutron guide optimization package
Home-page: https://git.esss.dk/highness/guide_bot
Author: Mads Bertelsen
Author-email: Mads.Bertelsen@ess.eu
License: UNKNOWN
Platform: UNKNOWN
Classifier: Programming Language :: Python :: 3
Classifier: License :: OSI Approved :: BSD License
Classifier: Operating System :: OS Independent
Classifier: Topic :: Scientific/Engineering
